{
  "version": "5.4.1",
  "flags": {},
  "shapes": [
    {
      "label": "zang_wu",
      "points": [
        [
          318.0,
          233.5
        ],
        [
          317.0,
          233.5
        ],
        [
          316.0,
          232.5
        ],
        [
          310.0,
          232.5
        ],
        [
          308.0,
          230.5
        ],
        [
          305.0,
          230.5
        ],
        [
          304.0,
          229.5
        ],
        [
          297.0,
          229.5
        ],
        [
          296.0,
          228.5
        ],
        [
          294.0,
          228.5
        ],
        [
          293.0,
          227.5
        ],
        [
          292.0,
          227.5
        ],
        [
          290.5,
          226.0
        ],
        [
          290.5,
          225.0
        ],
        [
          288.5,
          222.0
        ],
        [
          288.5,
          221.0
        ],
        [
          286.5,
          219.0
        ],
        [
          285.5,
          216.0
        ],
        [
          281.5,
          211.0
        ],
        [
          281.5,
          210.0
        ],
        [
          280.5,
          209.0
        ],
        [
          280.5,
          207.0
        ],
        [
          278.5,
          205.0
        ],
        [
          278.5,
          201.0
        ],
        [
          277.5,
          200.0
        ],
        [
          277.5,
          198.0
        ],
        [
          276.5,
          197.0
        ],
        [
          276.5,
          195.0
        ],
        [
          275.5,
          194.0
        ],
        [
          275.5,
          190.0
        ],
        [
          276.5,
          189.0
        ],
        [
          276.5,
          183.0
        ],
        [
          277.5,
          182.0
        ],
        [
          278.5,
          179.0
        ],
        [
          282.0,
          175.5
        ],
        [
          285.0,
          174.5
        ],
        [
          288.5,
          171.0
        ],
        [
          289.0,
          169.5
        ],
        [
          290.0,
          169.5
        ],
        [
          292.0,
          167.5
        ],
        [
          294.0,
          167.5
        ],
        [
          295.0,
          166.5
        ],
        [
          298.0,
          166.5
        ],
        [
          299.0,
          165.5
        ],
        [
          304.0,
          165.5
        ],
        [
          305.0,
          164.5
        ],
        [
          308.0,
          164.5
        ],
        [
          309.0,
          163.5
        ],
        [
          312.0,
          163.5
        ],
        [
          313.0,
          162.5
        ],
        [
          317.0,
          162.5
        ],
        [
          318.0,
          163.5
        ],
        [
          325.0,
          163.5
        ],
        [
          328.0,
          165.5
        ],
        [
          330.0,
          165.5
        ],
        [
          331.0,
          166.5
        ],
        [
          334.0,
          167.5
        ],
        [
          335.0,
          168.5
        ],
        [
          336.0,
          168.5
        ],
        [
          341.0,
          171.5
        ],
        [
          343.0,
          171.5
        ],
        [
          345.0,
          173.5
        ],
        [
          346.0,
          173.5
        ],
        [
          348.0,
          175.5
        ],
        [
          349.0,
          175.5
        ],
        [
          351.0,
          177.5
        ],
        [
          352.0,
          177.5
        ],
        [
          355.5,
          181.0
        ],
        [
          355.5,
          182.0
        ],
        [
          357.5,
          183.0
        ],
        [
          357.5,
          184.0
        ],
        [
          360.5,
          189.0
        ],
        [
          360.5,
          191.0
        ],
        [
          361.5,
          192.0
        ],
        [
          361.5,
          194.0
        ],
        [
          362.5,
          195.0
        ],
        [
          362.5,
          202.0
        ],
        [
          361.5,
          203.0
        ],
        [
          361.5,
          206.0
        ],
        [
          360.5,
          207.0
        ],
        [
          360.5,
          213.0
        ],
        [
          359.0,
          215.5
        ],
        [
          356.0,
          216.5
        ],
        [
          351.0,
          221.5
        ],
        [
          349.0,
          221.5
        ],
        [
          348.0,
          222.5
        ],
        [
          347.0,
          222.5
        ],
        [
          345.0,
          224.5
        ],
        [
          344.0,
          224.5
        ],
        [
          339.0,
          227.5
        ],
        [
          336.0,
          227.5
        ],
        [
          335.0,
          228.5
        ],
        [
          333.0,
          228.5
        ],
        [
          332.0,
          229.5
        ],
        [
          331.0,
          229.5
        ],
        [
          330.0,
          230.5
        ],
        [
          328.0,
          230.5
        ],
        [
          325.0,
          232.5
        ],
        [
          319.0,
          232.5
        ]
      ],
      "group_id": null,
      "description": "",
      "shape_type": "polygon",
      "flags": {},
      "mask": null
    },
    {
      "label": "zhen_kong",
      "points": [
        [
          304.0,
          328.5
        ],
        [
          300.0,
          328.5
        ],
        [
          298.5,
          327.0
        ],
        [
          298.5,
          322.0
        ],
        [
          299.0,
          321.5
        ],
        [
          301.0,
          321.5
        ],
        [
          302.0,
          320.5
        ],
        [
          303.0,
          321.5
        ],
        [
          304.0,
          321.5
        ],
        [
          305.5,
          323.0
        ],
        [
          305.5,
          326.0
        ],
        [
          304.5,
          327.0
        ],
        [
          304.5,
          328.0
        ]
      ],
      "group_id": null,
      "description": "",
      "shape_type": "polygon",
      "flags": {},
      "mask": null
    }
  ],
  "imagePath": "..\\images\\224.jpg",
  "imageData": null,
  "imageHeight": 480,
  "imageWidth": 640
}