{
  "version": "5.4.1",
  "flags": {},
  "shapes": [
    {
      "label": "zang_wu",
      "points": [
        [
          303.0,
          308.5
        ],
        [
          300.0,
          308.5
        ],
        [
          299.0,
          307.5
        ],
        [
          297.0,
          307.5
        ],
        [
          296.0,
          306.5
        ],
        [
          295.0,
          306.5
        ],
        [
          294.0,
          305.5
        ],
        [
          290.0,
          305.5
        ],
        [
          287.5,
          303.0
        ],
        [
          287.5,
          302.0
        ],
        [
          286.5,
          301.0
        ],
        [
          286.5,
          297.0
        ],
        [
          285.5,
          296.0
        ],
        [
          285.5,
          266.0
        ],
        [
          286.5,
          265.0
        ],
        [
          286.5,
          262.0
        ],
        [
          287.5,
          261.0
        ],
        [
          287.5,
          260.0
        ],
        [
          288.5,
          259.0
        ],
        [
          288.5,
          258.0
        ],
        [
          290.5,
          256.0
        ],
        [
          290.5,
          255.0
        ],
        [
          291.5,
          254.0
        ],
        [
          291.5,
          253.0
        ],
        [
          292.5,
          252.0
        ],
        [
          292.5,
          251.0
        ],
        [
          293.5,
          250.0
        ],
        [
          293.5,
          249.0
        ],
        [
          296.0,
          246.5
        ],
        [
          300.0,
          246.5
        ],
        [
          301.0,
          247.5
        ],
        [
          302.0,
          247.5
        ],
        [
          302.5,
          248.0
        ],
        [
          302.5,
          251.0
        ],
        [
          303.5,
          252.0
        ],
        [
          303.5,
          253.0
        ],
        [
          304.0,
          253.5
        ],
        [
          309.0,
          253.5
        ],
        [
          310.0,
          254.5
        ],
        [
          312.0,
          254.5
        ],
        [
          313.0,
          255.5
        ],
        [
          314.0,
          255.5
        ],
        [
          320.5,
          262.0
        ],
        [
          320.5,
          265.0
        ],
        [
          321.5,
          266.0
        ],
        [
          321.5,
          272.0
        ],
        [
          320.5,
          273.0
        ],
        [
          320.5,
          276.0
        ],
        [
          319.5,
          277.0
        ],
        [
          319.5,
          278.0
        ],
        [
          318.5,
          279.0
        ],
        [
          318.5,
          286.0
        ],
        [
          317.5,
          287.0
        ],
        [
          317.5,
          290.0
        ],
        [
          316.5,
          291.0
        ],
        [
          316.5,
          292.0
        ],
        [
          315.5,
          293.0
        ],
        [
          315.5,
          298.0
        ],
        [
          314.5,
          299.0
        ],
        [
          314.5,
          301.0
        ],
        [
          313.5,
          302.0
        ],
        [
          313.5,
          303.0
        ],
        [
          310.0,
          306.5
        ],
        [
          309.0,
          306.5
        ],
        [
          308.0,
          307.5
        ],
        [
          304.0,
          307.5
        ]
      ],
      "group_id": null,
      "description": "",
      "shape_type": "polygon",
      "flags": {},
      "mask": null
    },
    {
      "label": "zang_wu",
      "points": [
        [
          349.0,
          116.5
        ],
        [
          338.0,
          116.5
        ],
        [
          337.0,
          115.5
        ],
        [
          335.0,
          115.5
        ],
        [
          334.0,
          114.5
        ],
        [
          332.0,
          114.5
        ],
        [
          330.0,
          112.5
        ],
        [
          329.0,
          112.5
        ],
        [
          325.0,
          108.5
        ],
        [
          324.0,
          108.5
        ],
        [
          313.5,
          98.0
        ],
        [
          313.5,
          97.0
        ],
        [
          310.5,
          94.0
        ],
        [
          310.5,
          93.0
        ],
        [
          306.5,
          88.0
        ],
        [
          306.5,
          87.0
        ],
        [
          310.5,
          82.0
        ],
        [
          310.5,
          80.0
        ],
        [
          309.5,
          79.0
        ],
        [
          309.5,
          78.0
        ],
        [
          311.0,
          76.5
        ],
        [
          313.0,
          76.5
        ],
        [
          314.0,
          75.5
        ],
        [
          315.0,
          75.5
        ],
        [
          318.0,
          72.5
        ],
        [
          320.0,
          72.5
        ],
        [
          321.0,
          71.5
        ],
        [
          324.0,
          71.5
        ],
        [
          325.0,
          70.5
        ],
        [
          342.0,
          70.5
        ],
        [
          343.0,
          71.5
        ],
        [
          349.0,
          71.5
        ],
        [
          350.0,
          72.5
        ],
        [
          354.0,
          72.5
        ],
        [
          355.0,
          73.5
        ],
        [
          357.0,
          73.5
        ],
        [
          358.0,
          74.5
        ],
        [
          361.0,
          74.5
        ],
        [
          362.0,
          75.5
        ],
        [
          365.0,
          75.5
        ],
        [
          368.0,
          77.5
        ],
        [
          371.0,
          77.5
        ],
        [
          374.0,
          79.5
        ],
        [
          376.0,
          79.5
        ],
        [
          377.0,
          80.5
        ],
        [
          379.0,
          80.5
        ],
        [
          380.0,
          81.5
        ],
        [
          382.0,
          81.5
        ],
        [
          383.0,
          82.5
        ],
        [
          386.0,
          83.5
        ],
        [
          387.5,
          85.0
        ],
        [
          387.5,
          88.0
        ],
        [
          383.5,
          92.0
        ],
        [
          383.5,
          93.0
        ],
        [
          382.0,
          94.5
        ],
        [
          380.5,
          95.0
        ],
        [
          377.5,
          98.0
        ],
        [
          377.5,
          99.0
        ],
        [
          376.0,
          99.5
        ],
        [
          375.5,
          101.0
        ],
        [
          367.0,
          109.5
        ],
        [
          366.0,
          109.5
        ],
        [
          364.0,
          111.5
        ],
        [
          363.0,
          111.5
        ],
        [
          362.0,
          112.5
        ],
        [
          360.0,
          112.5
        ],
        [
          357.0,
          114.5
        ],
        [
          353.0,
          114.5
        ],
        [
          352.0,
          115.5
        ],
        [
          350.0,
          115.5
        ]
      ],
      "group_id": null,
      "description": "",
      "shape_type": "polygon",
      "flags": {},
      "mask": null
    },
    {
      "label": "zhe_zhou",
      "points": [
        [
          168.36363636363637,
          136.9090909090909
        ],
        [
          229.81818181818184,
          135.45454545454544
        ],
        [
          295.27272727272725,
          142.72727272727272
        ],
        [
          356.0,
          155.0909090909091
        ],
        [
          426.9090909090909,
          168.54545454545453
        ],
        [
          470.5454545454546,
          180.9090909090909
        ],
        [
          482.909090909091,
          191.8181818181818
        ],
        [
          482.18181818181824,
          219.0909090909091
        ],
        [
          481.0909090909091,
          232.54545454545453
        ],
        [
          428.3636363636364,
          227.8181818181818
        ],
        [
          352.72727272727275,
          210.36363636363635
        ],
        [
          262.5454545454545,
          191.45454545454544
        ],
        [
          187.63636363636363,
          176.1818181818182
        ],
        [
          160.0,
          169.27272727272728
        ],
        [
          160.72727272727272,
          155.8181818181818
        ]
      ],
      "group_id": null,
      "description": "",
      "shape_type": "polygon",
      "flags": {},
      "mask": null
    }
  ],
  "imagePath": "..\\images\\84.jpg",
  "imageData": null,
  "imageHeight": 480,
  "imageWidth": 640
}