{
  "version": "5.4.1",
  "flags": {},
  "shapes": [
    {
      "label": "zang_wu",
      "points": [
        [
          327.0,
          303.5
        ],
        [
          301.0,
          303.5
        ],
        [
          300.0,
          302.5
        ],
        [
          290.0,
          302.5
        ],
        [
          289.0,
          301.5
        ],
        [
          283.0,
          301.5
        ],
        [
          282.0,
          300.5
        ],
        [
          281.0,
          300.5
        ],
        [
          280.5,
          300.0
        ],
        [
          280.5,
          297.0
        ],
        [
          281.5,
          296.0
        ],
        [
          281.5,
          295.0
        ],
        [
          282.5,
          294.0
        ],
        [
          282.5,
          293.0
        ],
        [
          283.5,
          292.0
        ],
        [
          283.5,
          291.0
        ],
        [
          286.5,
          288.0
        ],
        [
          286.5,
          287.0
        ],
        [
          287.5,
          286.0
        ],
        [
          287.5,
          285.0
        ],
        [
          288.5,
          284.0
        ],
        [
          288.5,
          283.0
        ],
        [
          289.5,
          282.0
        ],
        [
          289.5,
          281.0
        ],
        [
          291.5,
          278.0
        ],
        [
          291.5,
          277.0
        ],
        [
          293.5,
          275.0
        ],
        [
          293.5,
          274.0
        ],
        [
          299.0,
          268.5
        ],
        [
          300.0,
          268.5
        ],
        [
          302.0,
          266.5
        ],
        [
          303.0,
          266.5
        ],
        [
          305.0,
          264.5
        ],
        [
          306.0,
          264.5
        ],
        [
          309.0,
          262.5
        ],
        [
          310.0,
          262.5
        ],
        [
          311.0,
          261.5
        ],
        [
          313.0,
          261.5
        ],
        [
          314.0,
          260.5
        ],
        [
          316.0,
          260.5
        ],
        [
          317.0,
          259.5
        ],
        [
          329.0,
          259.5
        ],
        [
          332.0,
          261.5
        ],
        [
          334.0,
          261.5
        ],
        [
          336.0,
          263.5
        ],
        [
          338.0,
          263.5
        ],
        [
          339.0,
          264.5
        ],
        [
          340.0,
          264.5
        ],
        [
          341.0,
          265.5
        ],
        [
          342.0,
          265.5
        ],
        [
          343.0,
          266.5
        ],
        [
          344.0,
          266.5
        ],
        [
          348.0,
          270.5
        ],
        [
          349.0,
          270.5
        ],
        [
          351.0,
          272.5
        ],
        [
          352.0,
          272.5
        ],
        [
          354.0,
          274.5
        ],
        [
          355.0,
          274.5
        ],
        [
          357.5,
          277.0
        ],
        [
          357.5,
          278.0
        ],
        [
          358.5,
          279.0
        ],
        [
          358.5,
          282.0
        ],
        [
          357.5,
          283.0
        ],
        [
          357.5,
          289.0
        ],
        [
          356.0,
          290.5
        ],
        [
          354.0,
          290.5
        ],
        [
          352.5,
          292.0
        ],
        [
          352.5,
          294.0
        ],
        [
          350.0,
          296.5
        ],
        [
          349.0,
          296.5
        ],
        [
          346.0,
          298.5
        ],
        [
          344.0,
          298.5
        ],
        [
          341.0,
          300.5
        ],
        [
          338.0,
          300.5
        ],
        [
          337.0,
          301.5
        ],
        [
          335.0,
          301.5
        ],
        [
          334.0,
          302.5
        ],
        [
          328.0,
          302.5
        ]
      ],
      "group_id": null,
      "description": "",
      "shape_type": "polygon",
      "flags": {},
      "mask": null
    },
    {
      "label": "zang_wu",
      "points": [
        [
          332.0,
          123.5
        ],
        [
          327.0,
          123.5
        ],
        [
          325.5,
          122.0
        ],
        [
          325.5,
          121.0
        ],
        [
          323.0,
          118.5
        ],
        [
          313.0,
          118.5
        ],
        [
          311.0,
          116.5
        ],
        [
          310.0,
          116.5
        ],
        [
          308.0,
          114.5
        ],
        [
          307.0,
          114.5
        ],
        [
          303.5,
          111.0
        ],
        [
          303.5,
          110.0
        ],
        [
          302.5,
          109.0
        ],
        [
          302.5,
          106.0
        ],
        [
          301.5,
          105.0
        ],
        [
          301.5,
          103.0
        ],
        [
          302.5,
          102.0
        ],
        [
          302.5,
          91.0
        ],
        [
          301.5,
          90.0
        ],
        [
          301.5,
          73.0
        ],
        [
          302.5,
          72.0
        ],
        [
          302.5,
          70.0
        ],
        [
          303.5,
          69.0
        ],
        [
          303.5,
          68.0
        ],
        [
          307.0,
          64.5
        ],
        [
          309.0,
          64.5
        ],
        [
          310.0,
          63.5
        ],
        [
          311.0,
          63.5
        ],
        [
          312.0,
          62.5
        ],
        [
          319.0,
          62.5
        ],
        [
          320.0,
          63.5
        ],
        [
          322.0,
          63.5
        ],
        [
          323.0,
          62.5
        ],
        [
          326.0,
          62.5
        ],
        [
          329.5,
          66.0
        ],
        [
          329.5,
          67.0
        ],
        [
          330.5,
          68.0
        ],
        [
          330.5,
          70.0
        ],
        [
          331.5,
          71.0
        ],
        [
          331.5,
          72.0
        ],
        [
          332.5,
          73.0
        ],
        [
          332.5,
          75.0
        ],
        [
          333.5,
          76.0
        ],
        [
          333.5,
          79.0
        ],
        [
          334.5,
          80.0
        ],
        [
          334.5,
          85.0
        ],
        [
          335.5,
          86.0
        ],
        [
          335.5,
          90.0
        ],
        [
          336.5,
          91.0
        ],
        [
          336.5,
          93.0
        ],
        [
          337.5,
          94.0
        ],
        [
          337.5,
          101.0
        ],
        [
          338.5,
          102.0
        ],
        [
          338.5,
          106.0
        ],
        [
          337.5,
          107.0
        ],
        [
          337.5,
          111.0
        ],
        [
          335.5,
          113.0
        ],
        [
          335.5,
          116.0
        ],
        [
          334.5,
          117.0
        ],
        [
          334.5,
          120.0
        ],
        [
          332.5,
          122.0
        ],
        [
          332.5,
          123.0
        ]
      ],
      "group_id": null,
      "description": "",
      "shape_type": "polygon",
      "flags": {},
      "mask": null
    },
    {
      "label": "zhe_zhou",
      "points": [
        [
          161.45454545454547,
          176.54545454545453
        ],
        [
          214.9090909090909,
          174.72727272727272
        ],
        [
          314.9090909090909,
          172.9090909090909
        ],
        [
          430.9090909090909,
          172.9090909090909
        ],
        [
          479.27272727272725,
          179.0909090909091
        ],
        [
          484.72727272727275,
          198.72727272727272
        ],
        [
          476.3636363636364,
          208.9090909090909
        ],
        [
          426.18181818181813,
          213.27272727272728
        ],
        [
          353.0909090909091,
          220.54545454545453
        ],
        [
          263.27272727272725,
          227.45454545454544
        ],
        [
          206.1818181818182,
          223.45454545454544
        ],
        [
          169.45454545454547,
          222.36363636363635
        ],
        [
          156.0,
          220.1818181818182
        ],
        [
          153.0909090909091,
          199.45454545454544
        ]
      ],
      "group_id": null,
      "description": "",
      "shape_type": "polygon",
      "flags": {},
      "mask": null
    }
  ],
  "imagePath": "..\\images\\88.jpg",
  "imageData": null,
  "imageHeight": 480,
  "imageWidth": 640
}